{
  "Ads": [
    {
      "select_main_ads": "ADMOB",
      "select_backup_ads":"APPLOVIN-M",
      "main_ads_banner": "ca-app-pub-3940256099942544/6300978111",
      "main_ads_intertitial":"ca-app-pub-3940256099942544/1033173712",
      "backup_ads_banner":"db4d5e8718b97d78",
      "backup_ads_intertitial":"518cd97722c60b52",
      "interval_intertitial": 1,
      "initialize_sdk":"107355779",
      "initialize_sdk_backup_ads":"",
      "high_paying_keyword_1": "",
      "high_paying_keyword_2": "",
      "high_paying_keyword_3": "",
      "high_paying_keyword_4": "",
      "high_paying_keyword_5": "",
      "status_app": "0",
      "link_redirect": "https://"
    }
  ],
  "Categories": [
    {
      "id": 1,
      "name_category": "Khalid Basalamah",
      "image": "file:///android_asset/image/khalid.jpg"
    },
    {
      "id": 2,
      "name_category": "Hanan Attaki",
      "image": "https://1.bp.blogspot.com/-HxYE662vYyY/XSKrn1Km7dI/AAAAAAACcPc/9lR7W3zPeW0P5Wk12D33pG6o81UkTOR8gCLcBGAs/s1600/Hanan%2BAttaki%2BUHA.jpg"
    },
    {
      "id": 3,
      "name_category": "Mr. Kim",
      "image": "file:///android_asset/image/kim.jpeg"
    },
    {
      "id": 4,
      "name_category": "Ammi Nur Bait",
      "image": "https://m.media-amazon.com/images/I/41sBIiTY2ZS._SL500_.jpg"
    },
    {
      "id": 4,
      "name_category": "Adi Hidayat",
      "image": "https://i0.wp.com/www.hops.id/wp-content/uploads/2021/06/ustadz-adi-hidayat-cov.jpg"
    }
  ],
"Data": [

    {
      "id": 1,
      "name_category": "Sidhu Mose Walla",
      "title": "295_Sidhu_Moose",
      "image": "file:///android_asset/image/sidhu.png",
      "link_mp3": "mp3/295_Sidhu_Moose.ogg",
      "duration": "300",
      "lyrics": "" },
    {
      "id": 2,
      "name_category": "Sidhu Mose Walla",
      "title": "Baapu_Sidhu_Moose_Wala",
      "image": "file:///android_asset/image/sidhu.png",
      "link_mp3": "mp3/Baapu_Sidhu_Moose_Wala.ogg",
      "duration": "300",
      "lyrics": "" },
    {
      "id": 3,
      "name_category": "Sidhu Mose Walla",
      "title": "BAMBIHA_BOLE",
      "image": "file:///android_asset/image/sidhu.png",
      "link_mp3": "mp3/BAMBIHA_BOLE.ogg",
      "duration": "300",
      "lyrics": "" },
    {
      "id": 4,
      "name_category": "Sidhu Mose Walla",
      "title": "Dark_Love",
      "image": "file:///android_asset/image/sidhu.png",
      "link_mp3": "mp3/Dark_Love.ogg",
      "duration": "300",
      "lyrics": "" },
    {
      "id": 5,
      "name_category": "Sidhu Mose Walla",
      "title": "DEAR_MAMA",
      "image": "file:///android_asset/image/sidhu.png",
      "link_mp3": "mp3/DEAR_MAMA.ogg",
      "duration": "300",
      "lyrics": "" },
    {
      "id": 6,
      "name_category": "Sidhu Mose Walla",
      "title": "DHAKKA",
      "image": "file:///android_asset/image/sidhu.png",
      "link_mp3": "mp3/DHAKKA.ogg",
      "duration": "300",
      "lyrics": "" },
    {
      "id": 7,
      "name_category": "Sidhu Mose Walla",
      "title": "GOAT",
      "image": "file:///android_asset/image/sidhu.png",
      "link_mp3": "mp3/GOAT.ogg",
      "duration": "300",
      "lyrics": "" },
    {
      "id": 8,
      "name_category": "Sidhu Mose Walla",
      "title": "HINT",
      "image": "file:///android_asset/image/sidhu.png",
      "link_mp3": "mp3/HINT.ogg",
      "duration": "300",
      "lyrics": "" },
    {
      "id": 9,
      "name_category": "Sidhu Mose Walla",
      "title": "LEGEND",
      "image": "file:///android_asset/image/sidhu.png",
      "link_mp3": "mp3/LEGEND.ogg",
      "duration": "300",
      "lyrics": "" },
    {
      "id": 10,
      "name_category": "Sidhu Mose Walla",
      "title": "LEVELS",
      "image": "file:///android_asset/image/sidhu.png",
      "link_mp3": "mp3/LEVELS.ogg",
      "duration": "300",
      "lyrics": "" },
    {
      "id": 11,
      "name_category": "Sidhu Mose Walla",
      "title": "ME_AND_MY_GIRLFRIEND",
      "image": "file:///android_asset/image/sidhu.png",
      "link_mp3": "mp3/ME_AND_MY_GIRLFRIEND.ogg",
      "duration": "300",
      "lyrics": "" },
    {
      "id": 12,
      "name_category": "Sidhu Mose Walla",
      "title": "OLD_SKOOL",
      "image": "file:///android_asset/image/sidhu.png",
      "link_mp3": "mp3/OLD_SKOOL.ogg",
      "duration": "300",
      "lyrics": "" },
    {
      "id": 13,
      "name_category": "Sidhu Mose Walla",
      "title": "SAME_BEEF",
      "image": "file:///android_asset/image/sidhu.png",
      "link_mp3": "mp3/SAME_BEEF.ogg",
      "duration": "300",
      "lyrics": "" },
    {
      "id": 14,
      "name_category": "Sidhu Mose Walla",
      "title": "SANJU",
      "image": "file:///android_asset/image/sidhu.png",
      "link_mp3": "mp3/SANJU.ogg",
      "duration": "300",
      "lyrics": "" },
    {
      "id": 15,
      "name_category": "Sidhu Mose Walla",
      "title": "SO_HIGH",
      "image": "file:///android_asset/image/sidhu.png",
      "link_mp3": "mp3/SO_HIGH.ogg",
      "duration": "300",
      "lyrics": "" },
    {
      "id": 16,
      "name_category": "Sidhu Mose Walla",
      "title": "So_High_BYG_BYRD",
      "image": "file:///android_asset/image/sidhu.png",
      "link_mp3": "mp3/So_High_BYG_BYRD.ogg",
      "duration": "300",
      "lyrics": "" },
    {
      "id": 17,
      "name_category": "Sidhu Mose Walla",
      "title": "TAARE",
      "image": "file:///android_asset/image/sidhu.png",
      "link_mp3": "mp3/TAARE.ogg",
      "duration": "300",
      "lyrics": "" },
    {
      "id": 18,
      "name_category": "Sidhu Mose Walla",
      "title": "THE_LAST_RIDE",
      "image": "file:///android_asset/image/sidhu.png",
      "link_mp3": "mp3/THE_LAST_RIDE.ogg",
      "duration": "300",
      "lyrics": "" },
    {
      "id": 19,
      "name_category": "Sidhu Mose Walla",
      "title": "TIBEYAN_DA_PUTT",
      "image": "file:///android_asset/image/sidhu.png",
      "link_mp3": "mp3/TIBEYAN_DA_PUTT.ogg",
      "duration": "300",
      "lyrics": ""
    }
  ,
    {
      "id": 20,
      "name_category": "Sidhu Mose Walla",
      "title": "TOCHAN",
      "image": "file:///android_asset/image/sidhu.png",
      "link_mp3": "mp3/TOCHAN.ogg",
      "duration": "300",
      "lyrics": ""
    }
  ]
